arraymap.cpython-39-i386-linux-gnu.so
arraymap-0.4.0.dist-info/top_level.txt
arraymap-0.4.0.dist-info/RECORD
arraymap-0.4.0.dist-info/LICENSE.md
arraymap-0.4.0.dist-info/METADATA
arraymap-0.4.0.dist-info/WHEEL
