Metadata-Version: 2.1
Name: arraymap
Version: 0.4.0
Summary: Dictionary-like lookup from NumPy array values to their integer positions
Home-page: https://github.com/static-frame/arraymap
Author: Christopher Ariza, Brandt Bucher
License: MIT
Classifier: Development Status :: 5 - Production/Stable
Classifier: Intended Audience :: Developers
Classifier: Topic :: Software Development
Classifier: License :: OSI Approved :: MIT License
Classifier: Operating System :: MacOS :: MacOS X
Classifier: Operating System :: Microsoft :: Windows
Classifier: Operating System :: POSIX
Classifier: Programming Language :: Python :: 3.9
Classifier: Programming Language :: Python :: 3.10
Classifier: Programming Language :: Python :: 3.11
Classifier: Programming Language :: Python :: 3.12
Classifier: Programming Language :: Python :: 3.13
Requires-Python: >=3.9
License-File: LICENSE.md
Requires-Dist: numpy>=1.19.5
